causalsoap/__init__.py
causalsoap/core.py
causalsoap-0.1.1.dist-info/licenses/LICENSE.txt
causalsoap-0.1.1.dist-info/METADATA
causalsoap-0.1.1.dist-info/WHEEL
causalsoap-0.1.1.dist-info/top_level.txt
causalsoap-0.1.1.dist-info/RECORD
