Metadata-Version: 2.4
Name: causalsoap
Version: 0.1.1
Summary: A causal feature selection (Causal DRIFT: Causal Dimensionality Reduction via Inference of Feature Treatments) library using residual-based ATE estimation.
Home-page: https://github.com/SakibHasanSimanto/deepCausal
Author: Kazi Sakib Hasan
Author-email: simanto.alt@gmail.com
Classifier: Programming Language :: Python :: 3
Classifier: License :: OSI Approved :: MIT License
Classifier: Operating System :: OS Independent
Requires-Python: >=3.7
License-File: LICENSE.txt
Requires-Dist: numpy
Requires-Dist: pandas
Requires-Dist: scikit-learn
Dynamic: author
Dynamic: author-email
Dynamic: classifier
Dynamic: description
Dynamic: description-content-type
Dynamic: home-page
Dynamic: license-file
Dynamic: requires-dist
Dynamic: requires-python
Dynamic: summary
